{"symbols":{},"files":{"src\\index.ts":"2024-06-30T11:28:49.143Z","src\\server.ts":"2024-06-30T11:28:49.250Z","src\\app\\config\\index.ts":"2024-06-30T11:28:49.120Z","src\\modules\\students\\student.interface.ts":"2024-06-30T11:28:49.186Z","src\\modules\\students\\student.model.ts":"2024-07-02T10:11:26.289Z","src\\modules\\students\\student.controller.ts":"2024-07-02T10:11:41.663Z","src\\modules\\students\\student.services.ts":"2024-07-02T09:18:29.012Z","src\\modules\\students\\student.route.ts":"2024-07-02T08:56:41.206Z","src\\modules\\teachers\\teacher.route.ts":"2024-06-29T18:03:38.005Z"}}